{
  "version": "0.2",
  "language": "en",
  "words": [
    "pykotor",
    "pykotorgl",
    "pykotorfont",
    "holocron",
    "holopatcher",
    "tslpatcher",
    "kotordiff",
    "batchpatcher",
    "guiconverter",
    "toolset",
    "resref",
    "resrefs",
    "strref",
    "chitin",
    "utc",
    "utd",
    "ute",
    "uti",
    "utm",
    "utp",
    "uts",
    "utt",
    "utw",
    "gff",
    "tpc",
    "txi",
    "tlk",
    "twoda",
    "bif",
    "erf",
    "rim",
    "mdl",
    "mdx",
    "lyt",
    "pth",
    "vis",
    "ncs",
    "nss",
    "git",
    "are",
    "ifo",
    "jrl",
    "gui",
    "ndix",
    "reone",
    "xoreos",
    "kotor",
    "kotors",
    "pazaak",
    "pylint",
    "pydocstyle",
    "precommit",
    "pre-commit",
    "codecov",
    "dependabot"
  ],
  "ignoreWords": [
    "vendor",
    "venv",
    "__pycache__"
  ],
  "ignorePaths": [
    "vendor/**",
    ".venv/**",
    "venv/**",
    "__pycache__/**",
    "*.pyc",
    "dist/**",
    "build/**",
    ".git/**"
  ]
}

